pymanopt/__init__.py
pymanopt/_version.py
pymanopt/function.py
pymanopt/autodiff/__init__.py
pymanopt/autodiff/backends/__init__.py
pymanopt/autodiff/backends/_autograd.py
pymanopt/autodiff/backends/_backend.py
pymanopt/autodiff/backends/_jax.py
pymanopt/autodiff/backends/_numpy.py
pymanopt/autodiff/backends/_pytorch.py
pymanopt/autodiff/backends/_tensorflow.py
pymanopt/core/__init__.py
pymanopt/core/problem.py
pymanopt/manifolds/__init__.py
pymanopt/manifolds/complex_circle.py
pymanopt/manifolds/euclidean.py
pymanopt/manifolds/fixed_rank.py
pymanopt/manifolds/grassmann.py
pymanopt/manifolds/group.py
pymanopt/manifolds/hyperbolic.py
pymanopt/manifolds/manifold.py
pymanopt/manifolds/oblique.py
pymanopt/manifolds/positive.py
pymanopt/manifolds/positive_definite.py
pymanopt/manifolds/product.py
pymanopt/manifolds/psd.py
pymanopt/manifolds/sphere.py
pymanopt/manifolds/stiefel.py
pymanopt/optimizers/__init__.py
pymanopt/optimizers/conjugate_gradient.py
pymanopt/optimizers/line_search.py
pymanopt/optimizers/nelder_mead.py
pymanopt/optimizers/optimizer.py
pymanopt/optimizers/particle_swarm.py
pymanopt/optimizers/steepest_descent.py
pymanopt/optimizers/trust_regions.py
pymanopt/tools/__init__.py
pymanopt/tools/diagnostics.py
pymanopt/tools/multi.py
pymanopt/tools/printer.py
pymanopt/tools/testing.py
pymanopt-2.2.1.dist-info/LICENSE
pymanopt-2.2.1.dist-info/METADATA
pymanopt-2.2.1.dist-info/WHEEL
pymanopt-2.2.1.dist-info/top_level.txt
pymanopt-2.2.1.dist-info/RECORD
